README.rst
setup.cfg
setup.py
redis_sort_queue/__init__.py
redis_sort_queue/collection_queues.py
redis_sort_queue/redis_queue.py
redis_sort_queue.egg-info/PKG-INFO
redis_sort_queue.egg-info/SOURCES.txt
redis_sort_queue.egg-info/dependency_links.txt
redis_sort_queue.egg-info/requires.txt
redis_sort_queue.egg-info/top_level.txt
redis_sort_queue/example/__init__.py
redis_sort_queue/example/client.py