Metadata-Version: 1.0
Name: redis-sort-queue
Version: 1.3.3
Summary: ordered queue for redis
Home-page: https://github.com/yordanglez/redis-sort-queue
Author: Yordano Gonzalez Fernandez
Author-email: yorda891216@gmail.com
License: UNKNOWN
Keywords: Redis,Queue,Priority,Sort
Platform: linux
